libfmp/__init__.py
libfmp/b/__init__.py
libfmp/b/b_annotation.py
libfmp/b/b_audio.py
libfmp/b/b_layout.py
libfmp/b/b_plot.py
libfmp/b/b_sonification.py
libfmp/b/b_test_module.py
libfmp/c1/__init__.py
libfmp/c1/c1s1_sheet_music.py
libfmp/c1/c1s2_symbolic_rep.py
libfmp/c1/c1s3_audio_rep.py
libfmp/c2/__init__.py
libfmp/c2/c2_complex.py
libfmp/c2/c2_digitization.py
libfmp/c2/c2_fourier.py
libfmp/c2/c2_interference.py
libfmp/c2/c2_interpolation.py
libfmp/c3/__init__.py
libfmp/c3/c3s1_audio_feature.py
libfmp/c3/c3s1_post_processing.py
libfmp/c3/c3s1_transposition_tuning.py
libfmp/c3/c3s2_dtw.py
libfmp/c3/c3s2_dtw_plot.py
libfmp/c3/c3s3_tempo_curve.py
libfmp/c4/__init__.py
libfmp/c4/c4s1_annotation.py
libfmp/c4/c4s2_ssm.py
libfmp/c4/c4s2_synthetic_ssm.py
libfmp/c4/c4s2_threshold.py
libfmp/c4/c4s3_thumbnail.py
libfmp/c4/c4s4_novelty_kernel.py
libfmp/c4/c4s4_structure_feature.py
libfmp/c4/c4s5_evaluation.py
libfmp/c5/__init__.py
libfmp/c5/c5s1_basic_theory_harmony.py
libfmp/c5/c5s2_chord_rec_template.py
libfmp/c5/c5s3_chord_rec_hmm.py
libfmp/c6/__init__.py
libfmp/c6/c6s1_onset_detection.py
libfmp/c6/c6s1_peak_picking.py
libfmp/c6/c6s2_tempo_analysis.py
libfmp/c6/c6s3_adaptive_windowing.py
libfmp/c6/c6s3_beat_tracking.py
libfmp/c7/__init__.py
libfmp/c7/c7s1_audio_id.py
libfmp/c7/c7s2_audio_matching.py
libfmp/c7/c7s3_version_id.py
libfmp/c8/__init__.py
libfmp/c8/c8s1_hps.py
libfmp/c8/c8s2_f0.py
libfmp/c8/c8s2_salience.py
libfmp/c8/c8s3_nmf.py
libfmp-1.2.6.dist-info/LICENSE
libfmp-1.2.6.dist-info/METADATA
libfmp-1.2.6.dist-info/WHEEL
libfmp-1.2.6.dist-info/top_level.txt
libfmp-1.2.6.dist-info/RECORD
