Metadata-Version: 2.1
Name: libfmp
Version: 1.2.6
Summary: Python module for fundamentals of music processing
Home-page: http://audiolabs-erlangen.de/FMP
Download-URL: https://github.com/meinardmueller/libfmp
Author: Meinard Müller and Frank Zalkow
Author-email: meinard.mueller@audiolabs-erlangen.de
License: MIT
Keywords: audio music sound
Classifier: License :: OSI Approved :: MIT License
Classifier: Programming Language :: Python
Classifier: Intended Audience :: Developers
Classifier: Topic :: Multimedia :: Sound/Audio :: Analysis
Classifier: Programming Language :: Python :: 3
Requires-Python: >=3.8
License-File: LICENSE
Requires-Dist: ipython <8.0.0,>=7.10.0
Requires-Dist: librosa <1.0.0,>=0.8.0
Requires-Dist: matplotlib <4.0.0,>=3.3.0
Requires-Dist: music21 <6.0.0,>=5.7.0
Requires-Dist: numba <1.0.0,>=0.56.0
Requires-Dist: numpy <2.0.0,>=1.19.0
Requires-Dist: pandas <3.0.0,>=1.1.0
Requires-Dist: pretty-midi <1.0.0,>=0.2.0
Requires-Dist: soundfile <1.0.0,>=0.9.0
Requires-Dist: scipy <2.0.0,>=1.5.0
Provides-Extra: tests
Requires-Dist: pytest ==6.2.* ; extra == 'tests'
